algo_trading_utils/__init__.py
algo_trading_utils/cryptofeed.py
algo_trading_utils/freqtrade/__init__.py
algo_trading_utils/freqtrade/start.py
algo_trading_utils/freqtrade/strategy.py
algo_trading_utils/postgres.py
algo_trading_utils-0.0.14.dist-info/METADATA
algo_trading_utils-0.0.14.dist-info/WHEEL
algo_trading_utils-0.0.14.dist-info/RECORD
