Metadata-Version: 2.1
Name: algo-trading-utils
Version: 0.0.14
Summary: 
Author: jamesbaber1
Author-email: 31859220+jamesbaber1@users.noreply.github.com
Requires-Python: >=3.9,<4.0.0
Classifier: Programming Language :: Python :: 3
Classifier: Programming Language :: Python :: 3.9
Classifier: Programming Language :: Python :: 3.10
Classifier: Programming Language :: Python :: 3.11
Classifier: Programming Language :: Python :: 3.12
Requires-Dist: pandas (>=2.1.3,<3.0.0)
Requires-Dist: psycopg2-binary (>=2.9.7)
Requires-Dist: tickerdax (>=0.0.83)
